dismalpy/__config__.py
dismalpy/__init__.py
dismalpy/model.py
dismalpy/requirements.txt
dismalpy/setup.py
dismalpy/version.py
dismalpy/_reg/__config__.py
dismalpy/_reg/__init__.py
dismalpy/_reg/_var.so
dismalpy/_reg/setup.py
dismalpy/_reg/sur.py
dismalpy/_reg/var.py
dismalpy/_stats/__config__.py
dismalpy/_stats/__init__.py
dismalpy/_stats/setup.py
dismalpy/_stats/rvs/__config__.py
dismalpy/_stats/rvs/__init__.py
dismalpy/_stats/rvs/_normal.so
dismalpy/_stats/rvs/_wishart.py
dismalpy/_stats/rvs/gamma.py
dismalpy/_stats/rvs/normal.py
dismalpy/_stats/rvs/rvs.py
dismalpy/_stats/rvs/setup.py
dismalpy/_stats/rvs/wishart.py
dismalpy/doc/__init__.py
dismalpy/doc/glossary.py
dismalpy/doc/jargon.py
dismalpy/src/__config__.py
dismalpy/src/__init__.py
dismalpy/src/blas.pxd
dismalpy/src/blas.so
dismalpy/src/capsule.h
dismalpy/src/lapack.pxd
dismalpy/src/lapack.so
dismalpy/src/math.pxd
dismalpy/src/setup.py
dismalpy/ssm/__config__.py
dismalpy/ssm/__init__.py
dismalpy/ssm/_favar.py
dismalpy/ssm/_kalman_filter.so
dismalpy/ssm/_kalman_smoother.so
dismalpy/ssm/_simulation_smoother.so
dismalpy/ssm/_statespace.so
dismalpy/ssm/_tools.so
dismalpy/ssm/composite.py
dismalpy/ssm/dynamic_factor.py
dismalpy/ssm/kalman_filter.py
dismalpy/ssm/kalman_smoother.py
dismalpy/ssm/likelihood_model.py
dismalpy/ssm/mlemodel.old.py
dismalpy/ssm/mlemodel.py
dismalpy/ssm/model.py
dismalpy/ssm/py_ssm.py
dismalpy/ssm/regime_switching.py
dismalpy/ssm/representation.py
dismalpy/ssm/sarimax.old.py
dismalpy/ssm/sarimax.py
dismalpy/ssm/setup.py
dismalpy/ssm/simulation_smoother.py
dismalpy/ssm/structural.py
dismalpy/ssm/structural_old.py
dismalpy/ssm/tools.py
dismalpy/ssm/var.py
dismalpy/ssm/varmax.py
dismalpy/ssm/_filters/__config__.py
dismalpy/ssm/_filters/__init__.py
dismalpy/ssm/_filters/_conventional.so
dismalpy/ssm/_filters/_inversions.so
dismalpy/ssm/_filters/_univariate.so
dismalpy/ssm/_filters/setup.py
dismalpy-0.2.3.dist-info/DESCRIPTION.rst
dismalpy-0.2.3.dist-info/METADATA
dismalpy-0.2.3.dist-info/RECORD
dismalpy-0.2.3.dist-info/WHEEL
dismalpy-0.2.3.dist-info/metadata.json
dismalpy-0.2.3.dist-info/top_level.txt
