Metadata-Version: 2.0
Name: dismalpy
Version: 0.2.3
Summary: DismalPy: a collection of resources for quantitative economics in Python.
Home-page: http://github.com/dismalpy/dismalpy
Author: Chad Fulton
Author-email: ChadFulton+pypi@gmail.com
License: Simplified-BSD
Platform: Windows
Platform: Linux
Platform: Solaris
Platform: Mac OS-X
Platform: Unix
Classifier: Development Status :: 4 - Beta
Classifier: Intended Audience :: Science/Research
Classifier: License :: OSI Approved :: BSD License
Classifier: Programming Language :: Cython
Classifier: Programming Language :: Python
Classifier: Programming Language :: Python :: 3
Classifier: Topic :: Scientific/Engineering
Classifier: Operating System :: Microsoft :: Windows
Classifier: Operating System :: POSIX
Classifier: Operating System :: Unix
Classifier: Operating System :: MacOS
Requires-Dist: Cython (>=0.20)
Requires-Dist: pandas (>=0.16.0)
Requires-Dist: scipy (>=0.14)
Requires-Dist: statsmodels (>=0.8)
